<?xml version="1.0" encoding="utf-8"?>
<rdf:RDF xmlns:rdf="http://www.w3.org/1999/02/22-rdf-syntax-ns#"
xmlns:rdfs="http://www.w3.org/2000/01/rdf-schema#"
xmlns:html="http://www.w3.org/1999/xhtml"
xmlns:rico="https://www.ica.org/standards/RiC/ontology#">
  <rico:Record rdf:resource="http://proxy.handle.net/10648/b57dca4c-e18a-4766-852b-dc1a903b0023"
  rdf:about="record/2.13.13.33">
    <rico:identifier>2.13.13.33</rico:identifier>
    <rico:hasDocumentaryFormType rdf:resource="https://www.ica.org/standards/RiC/vocabularies/documentaryFormTypes#FindingAid" />
    <rico:regulatedBy rdf:resource="http://id.loc.gov/vocabulary/iso639-2" />
    <rico:ruleFollowed xml:lang="en">ISAD(G): General International Standard Archival
    Description, International Council on Archives (2nd edition,
    2000).</rico:ruleFollowed>
    <rico:managedBy rdf:resource="agents/NL-HaNA">Nationaal Archief, Den
    Haag</rico:managedBy>
    <rico:publishedBy rdf:resource="agents/NL-HaNA">Nationaal Archief, Den
    Haag</rico:publishedBy>
    <rico:publicationDate rdf:datatype="http://www.w3.org/2001/XMLSchema#date">
    1949</rico:publicationDate>
    <rico:hasLanguage rdf:resource="http://id.loc.gov/vocabulary/iso639-2b/dut">
    Dutch</rico:hasLanguage>
    <rico:describes rdf:resource="recordResource/D27033" />
    <rico:hasInstantiation>
      <rico:Instantiation rdf:about="instantiation/2.13.13.33/i1" />
      <rico:instantiates rdf:resource="record/2.13.13.33" />
      <rico:history>
        <rico:hasModificationDate rdf:datatype="http://www.w3.org/2001/XMLSchema#date" />
        <html:p />
      </rico:history>
      <rico:title>
        <rico:textualValue>Inventaris van het archief van de Inspecteur-Generaal van de
        Administratie, (1808) 1814-1839</rico:textualValue>
      </rico:title>
      <rico:heldBy rdf:resource="agent/NL-HaNA" />
      <rdfs:seeAlso rdf:resource="http://proxy.handle.net/10648/b57dca4c-e18a-4766-852b-dc1a903b0023" />
      <rico:scopeAndContent rdf:parseType="Literal">
        <rdfs:label>Soort archiefmateriaal:</rdfs:label>
        <html:p>Normale geschreven, getypte en gedrukte documenten, geen bijzondere
        handschriften.</html:p>
      </rico:scopeAndContent>
    </rico:hasInstantiation>
  </rico:Record>
  <rico:RecordResource rdf:about="recordResource/D27033">
    <rico:describedBy rdf:resource="record/2.13.13.33" />
    <rdf:type rdf:resource="https://www.ica.org/standards/RiC/ontology#RecordSet" />
    <rico:hasRecordSetType rdf:resource="https://www.ica.org/standards/RiC/vocabularies/recordSetTypes#Collection" />
    <rico:identifier>D27033</rico:identifier>
    <rico:title>
      <rdfs:label>Naam archiefblok:</rdfs:label>
      <rico:textualValue>Inspecteur-Generaal van de Administratie bij het
      Leger</rico:textualValue>
    </rico:title>
    <rico:title>
      <rdf:type>urn:isbn:1-931666-22-9/type/short</rdf:type>
      <rico:textualValue>Isp.-Gen. Administratie Landmacht</rico:textualValue>
    </rico:title>
    <rico:beginningDate rdf:datatype="http://www.w3.org/2001/XMLSchema#gYear">
    1808</rico:beginningDate>
    <rico:endDate rdf:datatype="http://www.w3.org/2001/XMLSchema#gYear">
    1839</rico:endDate>
    <rico:date>1808-1839</rico:date>
    <rico:hasProvenance>
      <rico:Agent>
        <rdf:type rdf:resource="https://www.ica.org/standards/RiC/ontology#CorporateBody" />
        <rico:hasAgentName>
          <rico:AgentName>
            <rdfs:label>Inspecteur-Generaal van de Administratie bij het
            Leger</rdfs:label>
          </rico:AgentName>
        </rico:hasAgentName>
        <rico:history>
          <html:p>Het toezicht over de administratie bij het leger werd bij Soeverein
          Besluit van 10 januari 1814, nr. 33 opgedragen aan een commissaris voor de
          monsteringen, aan wie een aantal onder-commissarissen werd toegevoegd. Zij
          waren belast met het aanhouden der controles voor al de corpsen van het leger,
          het monsteren der troepen en het toezicht houden over de geregelde gang der
          administratie bij de corpsen.</html:p>
          <html:p>Ter vervanging van deze commissarissen werd bij Soeverein Besluit van
          20 februari 1815, nr. 20 een korps inspecteurs der administratie bij de armee
          opgericht. Aan het hoofd stond een inspecteur-generaal. Zijn instructie werd
          vastgesteld bij Soeverein Besluit van 20 februari 1815, nr. 21 (Bijvoegsel
          Stbl. 1815, IIde dl., blz. 274-305).</html:p>
        </rico:history>
      </rico:Agent>
    </rico:hasProvenance>
    <rico:scopeAndContent rdf:parseType="Literal">
      <rdfs:label>Samenvatting van de inhoud van het archief:</rdfs:label>
      <html:p>Het archief van de Inspecteur-Generaal van de Administratie bij het leger
      (1814 - 1839) bestaat o.a. correspondentie, akten van verpachting en contracten van
      levering, registers houdende aantekeningen van contracten en akten van verhuur,
      rang- en conduitelijsten van officieren en ridders der Militaire Willemsorde,
      sterktestaten, en stukken betreffende de geneeskundige dienst.</html:p>
    </rico:scopeAndContent>
    <rico:conditionsOfAccess rdf:parseType="Literal">
      <html:h2>Aanwijzingen voor de gebruiker</html:h2>
      <html:h3>Openbaarheidsbeperkingen</html:h3>
      <html:p>Volledig openbaar.</html:p>
      <html:h3>Beperkingen aan het gebruik</html:h3>
      <html:p>Reproductie van originele bescheiden uit dit archief is, behoudens de
      algemene regels die gelden voor het kopiëren van stukken, niet aan beperkingen
      onderhevig. Er zijn geen beperkingen krachtens het auteursrecht.</html:p>
    </rico:conditionsOfAccess>
    <rico:physicalOrLogicalExtent>
      <rdfs:label>Omvang:</rdfs:label>
      <rico:recordResourceExtent>
        <rdf:type>meter</rdf:type>
        <rdfs:label>3.10 meter;</rdfs:label>
      </rico:recordResourceExtent>
      <rico:recordResourceExtent>
        <rdf:type>files</rdf:type>
        <rdfs:label>33 inventarisnummers.</rdfs:label>
      </rico:recordResourceExtent>
    </rico:physicalOrLogicalExtent>
    <rico:descriptiveNote rdf:parseType="Literal">
      <html:div xml:lang="en">
        <html:h2>Verwant materiaal</html:h2>
        <html:h3>Beschikbaarheid van kopieën</html:h3>
        <html:p />
      </html:div>
    </rico:descriptiveNote>
  </rico:RecordResource>
</rdf:RDF>
