<?xml version="1.0" encoding="utf-8"?>
<rdf:RDF xmlns:rdf="http://www.w3.org/1999/02/22-rdf-syntax-ns#"
xmlns:rdfs="http://www.w3.org/2000/01/rdf-schema#"
xmlns:html="http://www.w3.org/1999/xhtml"
xmlns:rico="https://www.ica.org/standards/RiC/ontology#">
  <rico:Record rdf:resource="http://proxy.handle.net/10648/1d0575c8-2d67-4e19-9265-7e11cc37435e"
  rdf:about="record/2.20.34">
    <rico:identifier>2.20.34</rico:identifier>
    <rico:hasDocumentaryFormType rdf:resource="https://www.ica.org/standards/RiC/vocabularies/documentaryFormTypes#FindingAid" />
    <rico:regulatedBy rdf:resource="http://id.loc.gov/vocabulary/iso639-2" />
    <rico:ruleFollowed xml:lang="en">ISAD(G): General International Standard Archival
    Description, International Council on Archives (2nd edition,
    2000).</rico:ruleFollowed>
    <rico:managedBy rdf:resource="agents/NL-HaNA">Nationaal Archief, Den
    Haag</rico:managedBy>
    <rico:publishedBy rdf:resource="agents/NL-HaNA">Nationaal Archief, Den
    Haag</rico:publishedBy>
    <rico:publicationDate rdf:datatype="http://www.w3.org/2001/XMLSchema#date">
    1982</rico:publicationDate>
    <rico:hasLanguage rdf:resource="http://id.loc.gov/vocabulary/iso639-2b/dut">
    Dutch</rico:hasLanguage>
    <rico:describes rdf:resource="recordResource/I20591" />
    <rico:hasInstantiation>
      <rico:Instantiation rdf:about="instantiation/2.20.34/i1" />
      <rico:instantiates rdf:resource="record/2.20.34" />
      <rico:history>
        <rico:hasModificationDate rdf:datatype="http://www.w3.org/2001/XMLSchema#date">
        20121210</rico:hasModificationDate>
        <html:p>12 december 2013</html:p>
      </rico:history>
      <rico:history>
        <rico:hasModificationDate rdf:datatype="http://www.w3.org/2001/XMLSchema#date" />
        <html:p />
      </rico:history>
      <rico:title>
        <rico:textualValue>Inventaris van de archieven van het Indisch Comité voor
        Wetenschappelijke Onderzoekingen, 1888-1941; Natuurwetenschappelijke Raad van
        Nederlands-Indië, 1928-1941; Coördinatie Commissie voor Natuurwetenschappelijke
        Zaken, 1945-1948</rico:textualValue>
      </rico:title>
      <rico:heldBy rdf:resource="agent/NL-HaNA" />
      <rdfs:seeAlso rdf:resource="http://proxy.handle.net/10648/1d0575c8-2d67-4e19-9265-7e11cc37435e" />
      <rico:scopeAndContent rdf:parseType="Literal">
        <rdfs:label>Soort archiefmateriaal:</rdfs:label>
        <html:p>Normale geschreven, getypte en gedrukte documenten, geen bijzondere
        handschriften.</html:p>
      </rico:scopeAndContent>
    </rico:hasInstantiation>
  </rico:Record>
  <rico:RecordResource rdf:about="recordResource/I20591">
    <rico:describedBy rdf:resource="record/2.20.34" />
    <rdf:type rdf:resource="https://www.ica.org/standards/RiC/ontology#RecordSet" />
    <rico:hasRecordSetType rdf:resource="https://www.ica.org/standards/RiC/vocabularies/recordSetTypes#Collection" />
    <rico:identifier>I20591</rico:identifier>
    <rico:title>
      <rdfs:label>Naam archiefblok:</rdfs:label>
      <rico:textualValue>Indisch Comité Wetenschappelijk Onderzoek Natuurwetenschap
      (ICWO) en aanverwante archieven</rico:textualValue>
    </rico:title>
    <rico:title>
      <rdf:type>urn:isbn:1-931666-22-9/type/short</rdf:type>
      <rico:textualValue>Indisch Comité Wetenschappelijke
      Onderzoekingen</rico:textualValue>
    </rico:title>
    <rico:beginningDate rdf:datatype="http://www.w3.org/2001/XMLSchema#gYear">
    1888</rico:beginningDate>
    <rico:endDate rdf:datatype="http://www.w3.org/2001/XMLSchema#gYear">
    1948</rico:endDate>
    <rico:date>1888-1948</rico:date>
    <rico:hasProvenance>
      <rico:Agent>
        <rdf:type rdf:resource="https://www.ica.org/standards/RiC/ontology#CorporateBody" />
        <rico:hasAgentName>
          <rico:AgentName>
            <rdfs:label>Indisch Comité ter Bevordering van Natuurkundig Onderzoek der
            Nederlandsche Koloniën</rdfs:label>
          </rico:AgentName>
        </rico:hasAgentName>
        <rico:history />
      </rico:Agent>
      <rico:Agent>
        <rdf:type rdf:resource="https://www.ica.org/standards/RiC/ontology#CorporateBody" />
        <rico:hasAgentName>
          <rico:AgentName>
            <rdfs:label>Indisch Comité Wetenschappelijke Onderzoekingen</rdfs:label>
          </rico:AgentName>
        </rico:hasAgentName>
        <rico:history />
      </rico:Agent>
      <rico:Agent>
        <rdf:type rdf:resource="https://www.ica.org/standards/RiC/ontology#CorporateBody" />
        <rico:hasAgentName>
          <rico:AgentName>
            <rdfs:label>Natuurwetenschappelijke Raad van Nederlands-Indië</rdfs:label>
          </rico:AgentName>
        </rico:hasAgentName>
        <rico:history />
      </rico:Agent>
      <rico:Agent>
        <rdf:type rdf:resource="https://www.ica.org/standards/RiC/ontology#CorporateBody" />
        <rico:hasAgentName>
          <rico:AgentName>
            <rdfs:label>Coördinatie Commissie voor Natuurwetenschappelijke
            Zaken</rdfs:label>
          </rico:AgentName>
        </rico:hasAgentName>
        <rico:history />
      </rico:Agent>
    </rico:hasProvenance>
    <rico:scopeAndContent rdf:parseType="Literal">
      <rdfs:label>Samenvatting van de inhoud van het archief:</rdfs:label>
      <html:p>Het Indisch Comité voor Wetenschappelijke Onderzoekingen (I.C.W.O.) was een
      voortzetting van het in 1888 opgerichte "Indisch Comité ter bevordering van
      natuurkundig onderzoek der Nederlandsche koloniën". Tot de voornaamste taken van
      deze comités behoorden het uitbrengen van adviezen en inwinnen van inlichtingen met
      betrekking tot wetenschappelijke onderzoekingen, het voorbereiden van expedities en
      het verlenen van hulp aan in Nederlands-Indië werkzame onderzoekers. Het archief
      van het I.C.W.O. bevat o.a. notulen, correspondentie, financiële stukken en verder
      vooral stukken betreffende de exploratietochten en expedities.De
      Natuurwetenschappelijke Raad van Nederlandsch-Indië (N.W.R.) werd opgericht op 28
      februari 1928. Haar voornaamste rol lag in het adviseren van de Nederlands-Indische
      regering in zaken betrekking hebbende op natuurwetenschappelijke aangelegenheden.
      Ook het onderhouden van Internationale wetenschappelijke betrekkingen en het
      stimuleren en coördineren van natuurwetenschappelijk onderzoek behoorde tot haar
      taken. Het archief van de N.W.R. bevat jaarverslagen en correspondentie en verder
      stukken betreffende wetenschappelijke instituten.De Coördinatie Commissie voor
      Natuurwetenschappelijke Zaken (C.C.N.Z.) werd opgericht op 21 maart 1946. Net als
      de N.W.R. lag haar voornaamste taak in het adviseren van de (Nederlands-Indische)
      regering. Deze adviezen konden betrekking hebben op het (opnieuw na de oorlog doen)
      functioneren van wetenschappelijke instellingen, het coördineren van arbeid op
      wetenschappelijk gebied en het op peil brengen en houden van het gehele
      wetenschappelijke apparaat. Het archief van de C.C.N.Z. bevat notulen,
      correspondentie, stukken betreffende de organisatie, het financieel beheer en
      expedities, stukken betreffende wetenschappelijke instituten- en raden (waaronder
      richtlijnen) en wetenschappelijk onderzoek. Ook zijn er een aantal stukken met
      betrekking tot landbouw en visserij, met o.a. een stuk over de ontwikkeling van de
      landbouwbedrijven Java tijdens de Japanse bezetting.</html:p>
    </rico:scopeAndContent>
    <rico:conditionsOfAccess rdf:parseType="Literal">
      <html:h2>Aanwijzingen voor de gebruiker</html:h2>
      <html:h3>Openbaarheidsbeperkingen</html:h3>
      <html:p>Volledig openbaar.</html:p>
      <html:h3>Beperkingen aan het gebruik</html:h3>
      <html:p>Reproductie van originele bescheiden uit dit archief is, behoudens de
      algemene regels die gelden voor het kopiëren van stukken, niet aan beperkingen
      onderhevig. Er zijn geen beperkingen krachtens het auteursrecht.</html:p>
    </rico:conditionsOfAccess>
    <rico:physicalOrLogicalExtent>
      <rdfs:label>Omvang:</rdfs:label>
      <rico:recordResourceExtent>
        <rdf:type>meter</rdf:type>
        <rdfs:label>2.60 meter;</rdfs:label>
      </rico:recordResourceExtent>
      <rico:recordResourceExtent>
        <rdf:type>files</rdf:type>
        <rdfs:label>269 inventarisnummers.</rdfs:label>
      </rico:recordResourceExtent>
    </rico:physicalOrLogicalExtent>
    <rico:descriptiveNote rdf:parseType="Literal">
      <html:div xml:lang="en">
        <html:h2>Verwant materiaal</html:h2>
        <html:h3>Beschikbaarheid van kopieën</html:h3>
        <html:p />
      </html:div>
    </rico:descriptiveNote>
  </rico:RecordResource>
</rdf:RDF>
